<annotation>
	<folder>L</folder>
	<filename>Aya_L23.jpg</filename>
	<path>F:\term-2\GP\Handwave\Data\L\L23.jpg</path>
	<source>
		<database>Unknown</database>
	</source>
	<size>
		<width>640</width>
		<height>480</height>
		<depth>3</depth>
	</size>
	<segmented>0</segmented>
	<object>
		<name>L</name>
		<pose>Unspecified</pose>
		<truncated>0</truncated>
		<difficult>0</difficult>
		<bndbox>
			<xmin>352</xmin>
			<ymin>137</ymin>
			<xmax>517</xmax>
			<ymax>313</ymax>
		</bndbox>
	</object>
</annotation>